{"Stats Section with Header":{"Layout":"Single-column layout with a header section followed by a grid of statistics.","Design":"Clean and straightforward, focusing on key numbers with supportive text. The header section includes a title and a brief description.","Key Elements":{"Header Text":"Centered title with a subtitle providing context or an introduction.","Statistics Grid":"4-column grid layout on larger screens, containing individual stat blocks.","Stat Blocks":"Each block includes a number and a label, with uniform styling for coherence."},"Use Cases":"Ideal for showcasing team achievements, company metrics, or key performance indicators in a visually appealing format."}}